ppotp/__init__.py
ppotp/__main__.py
ppotp/__version__.py
ppotp/otp.py
ppotp-2.3.0.dist-info/LICENSE.txt
ppotp-2.3.0.dist-info/METADATA
ppotp-2.3.0.dist-info/WHEEL
ppotp-2.3.0.dist-info/entry_points.txt
ppotp-2.3.0.dist-info/top_level.txt
ppotp-2.3.0.dist-info/RECORD
